{
  "timestamp": "2025-12-06T22:20:38.557Z",
  "lastUpdated": "2025-12-06T22:20:38.557Z",
  "weather": {
    "temperature": 48,
    "feelsLike": 45,
    "humidity": 81,
    "pressure": "24.03",
    "windSpeed": 6,
    "windGust": 12,
    "windLull": 4,
    "windDirection": 215,
    "heatIndex": 48,
    "windChill": 45,
    "dewPoint": 42,
    "wetBulbTemperature": 45,
    "wetBulbGlobeTemperature": 46,
    "stationPressure": "24.03",
    "pressureTrend": "steady",
    "uvIndex": 1,
    "solarRadiation": 115,
    "brightness": 13790,
    "airDensity": "1.006",
    "deltaT": "1.7",
    "precipitation": "0.00",
    "precipitationRate": "0.00",
    "precipitationLastHour": "0.00",
    "precipitationFinal": "0.00",
    "lightningStrikes": 0,
    "lightningStrikesLastHour": 0,
    "lightningStrikesLast3Hours": 0,
    "lightningLastDistance": 40,
    "normalHigh": 52,
    "normalLow": 30,
    "normalPrecip": "0.10",
    "dataAvailable": true
  },
  "aircraft": {
    "total": 210,
    "commercial": 36,
    "generalAviation": 174,
    "lifeFlights": 0,
    "military": 0,
    "balloons": 0,
    "highestAltitude": 49000,
    "aircraftNearby": 0,
    "totalObservations": 4882,
    "dataAvailable": true
  },
  "seismic": {
    "totalObservations": 60,
    "activeChannels": 4,
    "dataQuality": 100,
    "stationHealth": "Excellent",
    "dataStatus": "No Data",
    "recentObservations": 0,
    "stationCode": "R923A",
    "networkCode": "AM",
    "maxSamples": 36864,
    "avgSamples": 32892,
    "sampleRate": 100,
    "recentEvents": 0,
    "totalHistoricalObservations": 1847293,
    "dataAvailable": true
  },
  "earthquakes": {
    "totalToday": 0,
    "within10mi": 0,
    "within25mi": 0,
    "significantEvents": 0,
    "largestMagnitude": 0,
    "recentEvents": [],
    "dataAvailable": true
  },
  "alerts": {
    "alertCount": 0,
    "alertTypes": [],
    "noSevereWeather": true,
    "statusMessage": "No severe weather alerts • All systems operational"
  },
  "system": {
    "allSystemsOperational": true,
    "dataUptime": 99.8,
    "lastMaintenance": "5 days ago",
    "sensorHealth": "All Good",
    "databaseRecords": 1847293,
    "nextCalibration": "14 days",
    "storageUsedGB": 47.3,
    "storageUsedPercent": 23
  }
}