{
  "timestamp": "2025-09-20T03:24:18.778Z",
  "lastUpdated": "2025-09-20T03:24:18.778Z",
  "weather": {
    "temperature": 76,
    "feelsLike": 76,
    "humidity": 69,
    "pressure": "24.10",
    "windSpeed": 2,
    "windGust": 6,
    "windLull": 0,
    "windDirection": 212,
    "heatIndex": 76,
    "windChill": 76,
    "dewPoint": 65,
    "wetBulbTemperature": 68,
    "wetBulbGlobeTemperature": 70,
    "stationPressure": "24.10",
    "pressureTrend": "steady",
    "uvIndex": 0,
    "solarRadiation": 0,
    "brightness": 0,
    "airDensity": "0.956",
    "deltaT": "4.3",
    "precipitation": "0.21",
    "precipitationRate": "0.00",
    "precipitationLastHour": "0.00",
    "precipitationFinal": "0.21",
    "lightningStrikes": 0,
    "lightningStrikesLastHour": 0,
    "lightningStrikesLast3Hours": 0,
    "lightningLastDistance": 5,
    "normalHigh": 84,
    "normalLow": 60,
    "normalPrecip": "0.23",
    "dataAvailable": true
  },
  "aircraft": {
    "total": 148,
    "commercial": 34,
    "generalAviation": 114,
    "lifeFlights": 1,
    "military": 0,
    "balloons": 0,
    "highestAltitude": 41000,
    "aircraftNearby": 0,
    "totalObservations": 3898,
    "dataAvailable": true
  },
  "seismic": {
    "totalObservations": 35,
    "activeChannels": 4,
    "dataQuality": 100,
    "stationHealth": "Excellent",
    "dataStatus": "No Data",
    "recentObservations": 0,
    "stationCode": "R923A",
    "networkCode": "AM",
    "maxSamples": 36864,
    "avgSamples": 29736,
    "sampleRate": 100,
    "recentEvents": 0,
    "totalHistoricalObservations": 1847293,
    "dataAvailable": true
  },
  "earthquakes": {
    "totalToday": 2,
    "within10mi": 0,
    "within25mi": 0,
    "significantEvents": 0,
    "largestMagnitude": 1.78,
    "recentEvents": [
      {
        "magnitude": 1.78,
        "location": "8 km ENE of Calumet, Oklahoma",
        "time": "2025-09-19T13:27:06.570Z",
        "distance": "42.7"
      },
      {
        "magnitude": 1.73,
        "location": "5 km E of Calumet, Oklahoma",
        "time": "2025-09-19T10:10:35.969Z",
        "distance": "41.6"
      }
    ],
    "dataAvailable": true
  },
  "alerts": {
    "alertCount": 0,
    "alertTypes": [],
    "noSevereWeather": true,
    "statusMessage": "No severe weather alerts • All systems operational"
  },
  "system": {
    "allSystemsOperational": true,
    "dataUptime": 99.8,
    "lastMaintenance": "5 days ago",
    "sensorHealth": "All Good",
    "databaseRecords": 1847293,
    "nextCalibration": "14 days",
    "storageUsedGB": 47.3,
    "storageUsedPercent": 23
  }
}