{
  "timestamp": "2025-09-26T14:32:18.628Z",
  "lastUpdated": "2025-09-26T14:32:18.628Z",
  "weather": {
    "temperature": 73,
    "feelsLike": 73,
    "humidity": 71,
    "pressure": "24.10",
    "windSpeed": 0,
    "windGust": 0,
    "windLull": 0,
    "windDirection": 0,
    "heatIndex": 73,
    "windChill": 73,
    "dewPoint": 63,
    "wetBulbTemperature": 66,
    "wetBulbGlobeTemperature": 72,
    "stationPressure": "24.10",
    "pressureTrend": "steady",
    "uvIndex": 3,
    "solarRadiation": 337,
    "brightness": 40497,
    "airDensity": "0.961",
    "deltaT": "3.9",
    "precipitation": "0.00",
    "precipitationRate": "0.00",
    "precipitationLastHour": "0.00",
    "precipitationFinal": "0.00",
    "lightningStrikes": 0,
    "lightningStrikesLastHour": 0,
    "lightningStrikesLast3Hours": 0,
    "lightningLastDistance": 39,
    "normalHigh": 81,
    "normalLow": 58,
    "normalPrecip": "0.22",
    "dataAvailable": true
  },
  "aircraft": {
    "total": 287,
    "commercial": 65,
    "generalAviation": 210,
    "lifeFlights": 1,
    "military": 11,
    "balloons": 1,
    "highestAltitude": 64000,
    "aircraftNearby": 0,
    "totalObservations": 6341,
    "dataAvailable": true
  },
  "seismic": {
    "totalObservations": 46,
    "activeChannels": 4,
    "dataQuality": 100,
    "stationHealth": "Excellent",
    "dataStatus": "No Data",
    "recentObservations": 0,
    "stationCode": "R923A",
    "networkCode": "AM",
    "maxSamples": 36864,
    "avgSamples": 30803,
    "sampleRate": 100,
    "recentEvents": 0,
    "totalHistoricalObservations": 1847293,
    "dataAvailable": true
  },
  "earthquakes": {
    "totalToday": 0,
    "within10mi": 0,
    "within25mi": 0,
    "significantEvents": 0,
    "largestMagnitude": 0,
    "recentEvents": [],
    "dataAvailable": true
  },
  "alerts": {
    "alertCount": 0,
    "alertTypes": [],
    "noSevereWeather": true,
    "statusMessage": "No severe weather alerts • All systems operational"
  },
  "system": {
    "allSystemsOperational": true,
    "dataUptime": 99.8,
    "lastMaintenance": "5 days ago",
    "sensorHealth": "All Good",
    "databaseRecords": 1847293,
    "nextCalibration": "14 days",
    "storageUsedGB": 47.3,
    "storageUsedPercent": 23
  }
}