{
  "timestamp": "2026-03-13T18:06:40.634Z",
  "lastUpdated": "2026-03-13T18:06:40.634Z",
  "weather": {
    "temperature": 64,
    "feelsLike": 64,
    "humidity": 35,
    "pressure": "24.08",
    "windSpeed": 6,
    "windGust": 10,
    "windLull": 1,
    "windDirection": 126,
    "heatIndex": 64,
    "windChill": 64,
    "dewPoint": 36,
    "wetBulbTemperature": 49,
    "wetBulbGlobeTemperature": 56,
    "stationPressure": "24.08",
    "pressureTrend": "steady",
    "uvIndex": 4,
    "solarRadiation": 711,
    "brightness": 85378,
    "airDensity": "0.977",
    "deltaT": "8.4",
    "precipitation": "0.00",
    "precipitationRate": "0.00",
    "precipitationLastHour": "0.00",
    "precipitationFinal": "0.00",
    "lightningStrikes": 0,
    "lightningStrikesLastHour": 0,
    "lightningStrikesLast3Hours": 0,
    "lightningLastDistance": 31,
    "normalHigh": 62,
    "normalLow": 38,
    "normalPrecip": "0.14",
    "dataAvailable": true
  },
  "aircraft": {
    "total": 329,
    "commercial": 58,
    "generalAviation": 258,
    "lifeFlights": 1,
    "military": 13,
    "balloons": 0,
    "highestAltitude": 49000,
    "aircraftNearby": 0,
    "totalObservations": 8082,
    "dataAvailable": true
  },
  "seismic": {
    "totalObservations": 72,
    "activeChannels": 4,
    "dataQuality": 100,
    "stationHealth": "Excellent",
    "dataStatus": "No Data",
    "recentObservations": 0,
    "stationCode": "R923A",
    "networkCode": "AM",
    "maxSamples": 36864,
    "avgSamples": 33584,
    "sampleRate": 100,
    "recentEvents": 0,
    "totalHistoricalObservations": 1847293,
    "dataAvailable": true
  },
  "earthquakes": {
    "totalToday": 1,
    "within10mi": 0,
    "within25mi": 0,
    "significantEvents": 0,
    "largestMagnitude": 1.69,
    "recentEvents": [
      {
        "magnitude": 1.69,
        "location": "6 km ENE of Calumet, Oklahoma",
        "time": "2026-03-12T19:41:31.940Z",
        "distance": "42.0"
      }
    ],
    "dataAvailable": true
  },
  "alerts": {
    "alertCount": 0,
    "alertTypes": [],
    "noSevereWeather": true,
    "statusMessage": "No severe weather alerts • All systems operational"
  },
  "system": {
    "allSystemsOperational": true,
    "dataUptime": 99.8,
    "lastMaintenance": "5 days ago",
    "sensorHealth": "All Good",
    "databaseRecords": 1847293,
    "nextCalibration": "14 days",
    "storageUsedGB": 47.3,
    "storageUsedPercent": 23
  }
}