{
  "timestamp": "2025-09-10T00:30:01.837Z",
  "lastUpdated": "2025-09-10T00:30:01.837Z",
  "weather": {
    "temperature": 82,
    "feelsLike": 83,
    "humidity": 52,
    "pressure": "24.11",
    "windSpeed": 6,
    "windGust": 10,
    "windLull": 1,
    "windDirection": 196,
    "heatIndex": 83,
    "windChill": 82,
    "dewPoint": 62,
    "wetBulbTemperature": 68,
    "wetBulbGlobeTemperature": 72,
    "stationPressure": "24.11",
    "pressureTrend": "steady",
    "uvIndex": 0,
    "solarRadiation": 14,
    "brightness": 1725,
    "airDensity": "0.946",
    "deltaT": "7.6",
    "precipitation": "0.00",
    "precipitationRate": "0.00",
    "precipitationLastHour": "0.00",
    "precipitationFinal": "0.00",
    "lightningStrikes": 0,
    "lightningStrikesLastHour": 0,
    "lightningStrikesLast3Hours": 0,
    "lightningLastDistance": 38,
    "normalHigh": 87,
    "normalLow": 64,
    "normalPrecip": "0.24",
    "dataAvailable": true
  },
  "aircraft": {
    "total": 212,
    "commercial": 69,
    "generalAviation": 142,
    "lifeFlights": 0,
    "military": 1,
    "balloons": 0,
    "highestAltitude": 45025,
    "aircraftNearby": 1,
    "totalObservations": 4891,
    "dataAvailable": true
  },
  "seismic": {
    "totalObservations": 42,
    "activeChannels": 4,
    "dataQuality": 100,
    "stationHealth": "Excellent",
    "dataStatus": "No Data",
    "recentObservations": 0,
    "stationCode": "R923A",
    "networkCode": "AM",
    "maxSamples": 36864,
    "avgSamples": 29080,
    "sampleRate": 100,
    "recentEvents": 0,
    "totalHistoricalObservations": 1847293,
    "dataAvailable": true
  },
  "earthquakes": {
    "totalToday": 4,
    "within10mi": 0,
    "within25mi": 0,
    "significantEvents": 1,
    "largestMagnitude": 3.14,
    "recentEvents": [
      {
        "magnitude": 3.14,
        "location": "7 km ENE of Calumet, Oklahoma",
        "time": "2025-09-10T00:12:33.434Z",
        "distance": "42.2"
      },
      {
        "magnitude": 2.2,
        "location": "7 km ENE of Calumet, Oklahoma",
        "time": "2025-09-10T00:08:00.244Z",
        "distance": "42.1"
      },
      {
        "magnitude": 1.63,
        "location": "7 km ENE of Calumet, Oklahoma",
        "time": "2025-09-09T09:32:23.550Z",
        "distance": "42.4"
      },
      {
        "magnitude": 1.61,
        "location": "7 km ENE of Calumet, Oklahoma",
        "time": "2025-09-09T02:28:02.209Z",
        "distance": "42.4"
      }
    ],
    "dataAvailable": true
  },
  "alerts": {
    "alertCount": 0,
    "alertTypes": [],
    "noSevereWeather": true,
    "statusMessage": "No severe weather alerts • All systems operational"
  },
  "system": {
    "allSystemsOperational": true,
    "dataUptime": 99.8,
    "lastMaintenance": "5 days ago",
    "sensorHealth": "All Good",
    "databaseRecords": 1847293,
    "nextCalibration": "14 days",
    "storageUsedGB": 47.3,
    "storageUsedPercent": 23
  }
}